what_to_eat/__init__.py
what_to_eat/__main__.py
what_to_eat/config.py
what_to_eat/controllers.py
what_to_eat/gateways/__init__.py
what_to_eat/gateways/location.py
what_to_eat/gateways/wolt.py
what_to_eat/main.py
what_to_eat/models/__init__.py
what_to_eat/models/config.py
what_to_eat/models/location.py
what_to_eat/models/query.py
what_to_eat/models/wolt.py
what_to_eat/services/__init__.py
what_to_eat/services/display.py
what_to_eat/services/filters.py
what_to_eat/services/profile.py
what_to_eat/services/weights.py
what_to_eat/utils/__init__.py
what_to_eat/utils/cache.py
what_to_eat/utils/handle.py
what_to_eat/utils/prompt.py
what_to_eat/utils/validators.py
what_to_eat-1.1.1.dist-info/LICENSE
what_to_eat-1.1.1.dist-info/METADATA
what_to_eat-1.1.1.dist-info/WHEEL
what_to_eat-1.1.1.dist-info/entry_points.txt
what_to_eat-1.1.1.dist-info/RECORD
