Metadata-Version: 2.1
Name: what-to-eat
Version: 1.1.1
Summary: What to eat? CLI tool to interaction with Wolt API
Author: Kamil Woźniak
Author-email: info@kamilwozniak.com
Requires-Python: >=3.12,<4.0
Classifier: Programming Language :: Python :: 3
Classifier: Programming Language :: Python :: 3.12
Requires-Dist: httpx (>=0.25.0,<0.26.0)
Requires-Dist: inquirer (>=2.10.1,<4.0.0)
Requires-Dist: pydantic (>=2.4.2,<3.0.0)
Requires-Dist: pydantic-settings (>=2.0.3,<3.0.0)
Requires-Dist: typer[all] (>=0.9.0,<0.10.0)
Project-URL: documentation, https://github.com/Valaraucoo/what-to-eat
Project-URL: homepage, https://github.com/Valaraucoo/what-to-eat
Project-URL: repository, https://github.com/Valaraucoo/what-to-eat
